.VERSION
AUTHORS.rst
CONTRIBUTING.rst
HISTORY.rst
LICENSE
MANIFEST.in
Pipfile
Pipfile.lock
README.rst
USAGE.rst
dev-requirements.txt
requirements.txt
setup.cfg
setup.py
docs/Makefile
docs/authors.rst
docs/conf.py
docs/contributing.rst
docs/history.rst
docs/index.rst
docs/installation.rst
docs/readme.rst
docs/usage.rst
sonosmusicservicelib/.VERSION
sonosmusicservicelib/AUTHORS.rst
sonosmusicservicelib/CONTRIBUTING.rst
sonosmusicservicelib/HISTORY.rst
sonosmusicservicelib/LICENSE
sonosmusicservicelib/Pipfile
sonosmusicservicelib/Pipfile.lock
sonosmusicservicelib/README.rst
sonosmusicservicelib/USAGE.rst
sonosmusicservicelib/__init__.py
sonosmusicservicelib/_version.py
sonosmusicservicelib/dev-requirements.txt
sonosmusicservicelib/requirements.txt
sonosmusicservicelib/serviceproxy.py
sonosmusicservicelib/sonosapplication.py
sonosmusicservicelib/sonosmusicservicelib.py
sonosmusicservicelib/sonosmusicservicelibexceptions.py
sonosmusicservicelib.egg-info/PKG-INFO
sonosmusicservicelib.egg-info/SOURCES.txt
sonosmusicservicelib.egg-info/dependency_links.txt
sonosmusicservicelib.egg-info/not-zip-safe
sonosmusicservicelib.egg-info/requires.txt
sonosmusicservicelib.egg-info/top_level.txt
tests/test_sonosmusicservicelib.py