Metadata-Version: 2.1
Name: sonosmusicservicelib
Version: 0.2.0
Summary: Template for Sonos Music services
Home-page: https://github.com/jendab/sonosmusicservicelib
Author: Jenda Brands
Author-email: jenda@brnds.eu
License: MIT
Keywords: sonosmusicservicelib
Classifier: Development Status :: 3 - Alpha
Classifier: Intended Audience :: Developers
Classifier: License :: OSI Approved :: MIT License
Classifier: Natural Language :: English
Classifier: Programming Language :: Python :: 3.9
License-File: LICENSE
License-File: AUTHORS.rst
Requires-Dist: spyne~=2.14.0
